imovel_scraper/__init__.py
imovel_scraper/__main__.py
imovel_scraper/py.typed
imovel_scraper-0.0.1.dist-info/entry_points.txt
imovel_scraper-0.0.1.dist-info/LICENSE.rst
imovel_scraper-0.0.1.dist-info/WHEEL
imovel_scraper-0.0.1.dist-info/METADATA
imovel_scraper-0.0.1.dist-info/RECORD
