Metadata-Version: 2.1
Name: imovel-scraper
Version: 0.0.1
Summary: Imovel Scraper
Home-page: https://github.com/acha-imovel/imovel-scraper
License: MIT
Author: Victor Mattos
Author-email: 5757883+vicmattos@users.noreply.github.com
Requires-Python: >=3.6.1,<4.0.0
Classifier: Development Status :: 1 - Planning
Classifier: License :: OSI Approved :: MIT License
Classifier: Programming Language :: Python :: 3
Classifier: Programming Language :: Python :: 3.6
Classifier: Programming Language :: Python :: 3.7
Classifier: Programming Language :: Python :: 3.8
Classifier: Programming Language :: Python :: 3.9
Requires-Dist: click (>=8.0.1,<9.0.0)
Project-URL: Changelog, https://github.com/acha-imovel/imovel-scraper/releases
Project-URL: Documentation, https://imovel-scraper.readthedocs.io
Project-URL: Repository, https://github.com/acha-imovel/imovel-scraper
